genetic_ml/__init__.py
genetic_ml/genetic.py
genetic_ML-0.0.1.dist-info/LICENSE
genetic_ML-0.0.1.dist-info/METADATA
genetic_ML-0.0.1.dist-info/WHEEL
genetic_ML-0.0.1.dist-info/top_level.txt
genetic_ML-0.0.1.dist-info/RECORD
