Metadata-Version: 2.1
Name: genetic-ML
Version: 0.0.1
Summary: in construction
Home-page: https://github.com/eliottkalfon
Author: Eliot Kalfon
Author-email: eliott.kalfon@gmail.com
License: UNKNOWN
Platform: UNKNOWN
Classifier: Programming Language :: Python :: 3
Classifier: License :: OSI Approved :: MIT License
Classifier: Operating System :: OS Independent
Requires-Python: >=3.6
